.DS_Store
cece/__init__.py
cece/graph.py
cece/queries.py
cece/refine.py
cece/wordnet.py
cece/xDataset.py
cece-0.1.1.dist-info/LICENSE
cece-0.1.1.dist-info/METADATA
cece-0.1.1.dist-info/WHEEL
cece-0.1.1.dist-info/top_level.txt
cece-0.1.1.dist-info/RECORD
