Metadata-Version: 2.1
Name: cece
Version: 0.1.1
Summary: Conceptual Edits as Counterfactual Explanations
Home-page: UNKNOWN
Author: Giorgos Filandrianos
Author-email: georgefilandr@gmail.com
License: MIT
Platform: UNKNOWN
Classifier: License :: OSI Approved :: MIT License
Classifier: Programming Language :: Python :: 3.10
Classifier: Operating System :: OS Independent
Requires-Python: >=3.8.8
Requires-Dist: numpy (>=1.20.1)
Requires-Dist: networkx (>=2.5)
Provides-Extra: dev
Requires-Dist: twine (>=4.0.2) ; extra == 'dev'
